volatus/__init__.py
volatus/config.py
volatus/discovery.py
volatus/messaging.py
volatus/telemetry.py
volatus/volatus.py
volatus/proto/__init__.py
volatus/proto/cmd_analog_pb2.py
volatus/proto/cmd_analog_pb2.pyi
volatus/proto/cmd_digital_pb2.py
volatus/proto/cmd_digital_pb2.pyi
volatus/proto/doubles_pb2.py
volatus/proto/doubles_pb2.pyi
volatus/proto/event_pb2.py
volatus/proto/event_pb2.pyi
volatus/proto/start_log_pb2.py
volatus/proto/start_log_pb2.pyi
volatus/proto/start_seq_pb2.py
volatus/proto/start_seq_pb2.pyi
volatus/proto/stop_log_pb2.py
volatus/proto/stop_log_pb2.pyi
volatus/proto/sync_ticks_pb2.py
volatus/proto/sync_ticks_pb2.pyi
volatus/vecto/TCP.py
volatus/vecto/UDP.py
volatus/vecto/__init__.py
volatus/vecto/util.py
volatus/vecto/proto/__init__.py
volatus/vecto/proto/discovery_pb2.py
volatus/vecto/proto/discovery_pb2.pyi
volatus/vecto/proto/empty_pb2.py
volatus/vecto/proto/empty_pb2.pyi
volatus/vecto/proto/group_data_pb2.py
volatus/vecto/proto/group_data_pb2.pyi
volatus/vecto/proto/string_data_pb2.py
volatus/vecto/proto/string_data_pb2.pyi
volatus/vecto/proto/stringtest_pb2.py
volatus/vecto/proto/stringtest_pb2.pyi
volatus/vecto/proto/tcp_ack_nack_pb2.py
volatus/vecto/proto/tcp_ack_nack_pb2.pyi
volatus/vecto/proto/tcp_client_hello_pb2.py
volatus/vecto/proto/tcp_client_hello_pb2.pyi
volatus/vecto/proto/tcp_payload_pb2.py
volatus/vecto/proto/tcp_payload_pb2.pyi
volatus/vecto/proto/tcp_reply_pb2.py
volatus/vecto/proto/tcp_reply_pb2.pyi
volatus/vecto/proto/tcp_server_hello_pb2.py
volatus/vecto/proto/tcp_server_hello_pb2.pyi
volatus/vecto/proto/udp_payload_pb2.py
volatus/vecto/proto/udp_payload_pb2.pyi
ig_volatus-0.6.2.dist-info/METADATA
ig_volatus-0.6.2.dist-info/WHEEL
ig_volatus-0.6.2.dist-info/RECORD
