Metadata-Version: 2.4
Name: ig-volatus
Version: 0.6.2
Summary: Python package for interacting with Volatus framework applications
Author-email: Derrick Bommarito <derrick.a.bommarito@gmail.com>
License: MIT
Requires-Python: >=3.13
Requires-Dist: aiofiles>=24.1.0
Requires-Dist: aiohttp>=3.12.15
Requires-Dist: fastapi>=0.117.1
Requires-Dist: netifaces-plus>=0.12.4
Requires-Dist: protobuf<7.0.0,>=6.32.0
Requires-Dist: requests<3.0.0,>=2.32.5
Requires-Dist: sockets<2.0.0,>=1.0.0
